pypcie/__init__.py
pypcie/bar.py
pypcie/device.py
pypcie-0.1.2.dist-info/licenses/LICENSE
pypcie-0.1.2.dist-info/METADATA
pypcie-0.1.2.dist-info/WHEEL
pypcie-0.1.2.dist-info/top_level.txt
pypcie-0.1.2.dist-info/RECORD
