Metadata-Version: 2.4
Name: pyPCIe
Version: 0.1.2
Summary: Simple Python module to access PCIe devices
Home-page: https://github.com/heikoengel/pyPCIe
Author: Heiko Engel
Author-email: <heikoengel@users.noreply.github.com>
Keywords: python,pcie
Classifier: Development Status :: 3 - Alpha
Classifier: Programming Language :: Python :: 3
Classifier: License :: OSI Approved :: MIT License
Classifier: Operating System :: POSIX :: Linux
License-File: LICENSE
Dynamic: author
Dynamic: author-email
Dynamic: classifier
Dynamic: description
Dynamic: description-content-type
Dynamic: home-page
Dynamic: keywords
Dynamic: license-file
Dynamic: summary
